{
  "resourceType": "Organization",
  "id": "b3038360-2804-4469-921c-a842836dd49a",
  "identifier": [
    {
      "use": "official",
      "type": {
        "coding": [
          {
            "system": "http://terminology.hl7.org/CodeSystem/v2-0203",
            "code": "NPI",
            "display": "National Provider Identifier"
          }
        ],
        "text": "National Provider Identifier"
      },
      "system": "http://hl7.org/fhir/sid/us-npi",
      "value": "1548273016"
    }
  ],
  "active": true,
  "type": [
    {
      "coding": [
        {
          "system": "http://terminology.hl7.org/CodeSystem/organization-type",
          "code": "prov",
          "display": "Healthcare Provider"
        }
      ],
      "text": "Healthcare Provider"
    }
  ],
  "name": "Houston Pulmonary Associates",
  "telecom": [
    {
      "system": "phone",
      "value": "713-555-0190",
      "use": "work"
    },
    {
      "system": "fax",
      "value": "713-555-0191",
      "use": "work"
    }
  ],
  "address": [
    {
      "use": "work",
      "line": [
        "6624 Fannin St",
        "Suite 1540"
      ],
      "city": "Houston",
      "state": "TX",
      "postalCode": "77030",
      "country": "US"
    }
  ]
}
