{
  "resourceType": "Observation",
  "id": "enc-005-tjc28",
  "status": "final",
  "category": [
    {
      "coding": [
        {
          "system": "http://terminology.hl7.org/CodeSystem/observation-category",
          "code": "survey",
          "display": "Survey"
        }
      ],
      "text": "Survey"
    }
  ],
  "code": {
    "coding": [
      {
        "system": "http://loinc.org",
        "code": "88981-6",
        "display": "Tender joint #"
      }
    ],
    "text": "Tender joint count (28-joint assessment)"
  },
  "subject": {
    "reference": "Patient/d52e98af-b701-422a-9dba-faf6ebf1cd84",
    "display": "Carlos Antonio Medina"
  },
  "encounter": {
    "reference": "Encounter/enc-005"
  },
  "effectiveDateTime": "2021-03-15",
  "valueQuantity": {
    "value": 12,
    "unit": "{joints}",
    "system": "http://unitsofmeasure.org",
    "code": "{joints}"
  }
}
