{
  "resourceType": "MedicationRequest",
  "id": "enc-015-acetaminophen",
  "status": "active",
  "intent": "order",
  "category": [
    {
      "coding": [
        {
          "system": "http://terminology.hl7.org/CodeSystem/medicationrequest-category",
          "code": "discharge",
          "display": "Discharge"
        }
      ],
      "text": "Discharge"
    }
  ],
  "medicationCodeableConcept": {
    "coding": [
      {
        "system": "http://www.nlm.nih.gov/research/umls/rxnorm",
        "code": "198440",
        "display": "acetaminophen 500 MG Oral Tablet"
      }
    ],
    "text": "Acetaminophen 500 mg oral tablet"
  },
  "subject": {
    "reference": "Patient/c36da299-c712-41bf-9f10-4c45a8beab7a",
    "display": "Harold James Washington"
  },
  "encounter": {
    "reference": "Encounter/enc-015"
  },
  "authoredOn": "2025-02-08",
  "requester": {
    "reference": "Practitioner/1e81f11b-717d-4e7d-9780-8bf094efcf80",
    "display": "Dr. Marcus Williams"
  },
  "reasonReference": [
    {
      "reference": "Condition/enc-015-laceration",
      "display": "Laceration of forehead"
    },
    {
      "reference": "Condition/enc-015-wrist-contusion",
      "display": "Contusion of right wrist"
    }
  ],
  "dosageInstruction": [
    {
      "text": "Take 500 mg by mouth every 6 hours as needed for pain. Do not exceed 2000 mg per day.",
      "patientInstruction": "Take 500 mg by mouth every 6 hours as needed for pain. Do not exceed 2000 mg per day.",
      "timing": {
        "repeat": {
          "frequency": 1,
          "period": 6,
          "periodUnit": "h"
        }
      },
      "asNeededBoolean": true,
      "route": {
        "coding": [
          {
            "system": "http://snomed.info/sct",
            "code": "738956005",
            "display": "Oral (intended site)"
          }
        ],
        "text": "Oral"
      },
      "doseAndRate": [
        {
          "doseQuantity": {
            "value": 500,
            "unit": "mg",
            "system": "http://unitsofmeasure.org",
            "code": "mg"
          }
        }
      ],
      "maxDosePerPeriod": {
        "numerator": {
          "value": 2000,
          "unit": "mg",
          "system": "http://unitsofmeasure.org",
          "code": "mg"
        },
        "denominator": {
          "value": 1,
          "unit": "day",
          "system": "http://unitsofmeasure.org",
          "code": "d"
        }
      }
    }
  ]
}
